arxiv_filter/__init__.py
arxiv_filter/__main__.py
arxiv_filter/arxiv/__init__.py
arxiv_filter/arxiv/entry.py
arxiv_filter/arxiv/filter.py
arxiv_filter/arxiv/parser.py
arxiv_filter/arxiv/scored_entry.py
arxiv_filter/arxiv/util.py
arxiv_filter/config/Definition.py
arxiv_filter/config/DefinitionLoader.py
arxiv_filter/config/__init__.py
arxiv_filter/ui/ArxivFilter.py
arxiv_filter/ui/ListEntry.py
arxiv_filter/ui/ListView.py
arxiv_filter/ui/ParserThread.py
arxiv_filter/ui/__init__.py
arxiv_filter-0.4.0.dist-info/LICENSE
arxiv_filter-0.4.0.dist-info/METADATA
arxiv_filter-0.4.0.dist-info/WHEEL
arxiv_filter-0.4.0.dist-info/entry_points.txt
arxiv_filter-0.4.0.dist-info/top_level.txt
arxiv_filter-0.4.0.dist-info/RECORD
