Metadata-Version: 2.1
Name: arxiv-filter
Version: 0.4.0
Summary: Quickly filter the daily arXiv email for your interests.
Home-page: https://github.com/deragent/arXivFilter
Author: deragent
Author-email: github@deragent.net
License: MIT
Classifier: License :: OSI Approved :: MIT License
Classifier: Programming Language :: Python :: 3
Classifier: Programming Language :: Python :: 3.7
License-File: LICENSE
Requires-Dist: pyyaml
Requires-Dist: PyQt5
